CHANGES.rst
LICENSE
MANIFEST.in
README.rst
setup.cfg
setup.py
tox.ini
bin/jep
bin/jep.bat
docs/CHANGES.rst
docs/Exception-Handling.rst
docs/FAQ.rst
docs/Getting-Started.rst
docs/How-Jep-Works.rst
docs/Interactive-Console.rst
docs/Jep-and-the-GIL.rst
docs/Linux.rst
docs/Naming-Conflicts.rst
docs/Numpy-Usage.rst
docs/OS-X.rst
docs/Operating-System-Specifics.rst
docs/Performance-Considerations.rst
docs/README.rst
docs/Windows.rst
docs/Workarounds-for-CPython-Extensions.rst
docs/conf.py
docs/index.rst
docs/_static/.keep
docs/_templates/.keep
src/jt/__init__.py
src/jt/jep.cfg
src/jt/jep/__about__.py
src/jt/jep/__config__.py
src/jt/jep/__init__.py
src/jt/jep/_jpackage.py
src/jt/jep/console.py
src/jt/jep/java_import_hook.py
src/jt/jep/jdbc.py
src/jt/jep/redirect_streams.py
src/jt/jep/shared_modules_hook.py
src/jt/jep/version.py
src/jt/jep/_java/__init__.py
src/jt/jep/_java/class2py.py
src/jt/jep/_java/jep/Jep.java
src/jt/jep/_java/jep/Jep.py
src/jt/jep/_java/jep/JepConfig.java
src/jt/jep/_java/jep/JepException.java
src/jt/jep/_java/jep/JepException.py
src/jt/jep/_java/jep/MainInterpreter.java
src/jt/jep/_java/jep/MainInterpreter.py
src/jt/jep/_java/jep/PyConfig.java
src/jt/jep/_java/jep/Run.java
src/jt/jep/_java/jep/__init__.py
src/jt/jep/_java/jep/python/PyClass.java
src/jt/jep/_java/jep/python/PyClass.py
src/jt/jep/_java/jep/python/PyModule.java
src/jt/jep/_java/jep/python/PyModule.py
src/jt/jep/_java/jep/python/PyObject.java
src/jt/jep/_java/jep/python/PyObject.py
src/jt/jep/_java/jep/python/__init__.py
src/jt/jep/_java/jep/reflect/__init__.py
src/jt/jep/_jep/__init__.py
src/jt/jep/_jep/_constants.py
src/jt/jep/_jep/_exceptions.py
src/jt/jep/_jep/_jarray.py
src/jt/jep/_jep/_jautocloseable.py
src/jt/jep/_jep/_jclass.py
src/jt/jep/_jep/_jcollection.py
src/jt/jep/_jep/_jfield.py
src/jt/jep/_jep/_jmethod.py
src/jt/jep/_jep/_jmonitor.py
src/jt/jep/_jep/_jnumber.py
src/jt/jep/_jep/_jobject.py
src/jt/jep/_jep/_jvm.py
src/jt/jep/_jep/_main.py
src/jt/jep/_jep/_typemanager.py
src/jtypes.jep.egg-info/PKG-INFO
src/jtypes.jep.egg-info/SOURCES.txt
src/jtypes.jep.egg-info/dependency_links.txt
src/jtypes.jep.egg-info/namespace_packages.txt
src/jtypes.jep.egg-info/requires.txt
src/jtypes.jep.egg-info/top_level.txt
src/jtypes.jep.egg-info/zip-safe
